poetry_pyinstaller_plugin/__init__.py
poetry_pyinstaller_plugin/hooks.py
poetry_pyinstaller_plugin/plugin.py
poetry_pyinstaller_plugin/target.py
poetry_pyinstaller_plugin/utils.py
poetry_pyinstaller_plugin-2.0.2.dist-info/METADATA
poetry_pyinstaller_plugin-2.0.2.dist-info/WHEEL
poetry_pyinstaller_plugin-2.0.2.dist-info/entry_points.txt
poetry_pyinstaller_plugin-2.0.2.dist-info/licenses/LICENSE
poetry_pyinstaller_plugin-2.0.2.dist-info/RECORD
