Metadata-Version: 2.4
Name: poetry-pyinstaller-plugin
Version: 2.0.2
Summary: Poetry plugin to build and/or bundle executable binaries with PyInstaller
License: MIT
License-File: LICENSE
Keywords: poetry,plugin,pyinstaller,binary
Author: Thomas Mahé
Author-email: contact@tmahe.dev
Maintainer: Thomas Mahé
Maintainer-email: contact@tmahe.dev
Requires-Python: >=3.10,<3.15
Classifier: Development Status :: 3 - Alpha
Classifier: Environment :: Plugins
Classifier: Intended Audience :: Developers
Classifier: License :: OSI Approved :: MIT License
Classifier: Operating System :: POSIX :: Linux
Classifier: Operating System :: Microsoft :: Windows
Classifier: Natural Language :: English
Classifier: Programming Language :: Python
Classifier: Programming Language :: Python :: 3
Classifier: Topic :: Software Development :: Build Tools
Classifier: Topic :: System :: Software Distribution
Classifier: Topic :: Software Development :: Libraries :: Python Modules
Classifier: Topic :: System :: Installation/Setup
Classifier: Topic :: Utilities
